Metadata-Version: 1.0
Name: arnobsprob-dist
Version: 0.1
Summary: Gaussian distributions
Home-page: UNKNOWN
Author: Syed Sanzam
Author-email: UNKNOWN
License: UNKNOWN
Platform: UNKNOWN
